Workbook

Sheet Сводка
A1: Рынок маркетплейсов Казахстана: потенциал продаж до 2030 года
A2: Сценарий меняется на листе «Допущения», ячейка C3. Все цифры — млрд ₸, если не указано иное.
A4: Выбранный сценарий | B4: =Допущения!C3 -> Базовый
A6: Рынок e-commerce 2025 | B6: =Рынок!B39 -> 4920
A7: Рынок e-commerce 2030 | B7: =Рынок!G39 -> 11100
A8: Прирост 2025–2030 | B8: =B7-B6 -> 6180
A9: Рост рынка в год (CAGR) | B9: =Рынок!B44 -> 0.17671577
A10: Внутренний сегмент 2030 | B10: =Рынок!G37 -> 7548
A11: Трансграничный сегмент 2030 | B11: =Рынок!G38 -> 3552
A12: Доля внутреннего e-commerce в рознице 2030 | B12: =Рынок!G42 -> 0.18613684
A13: Заказы на маркетплейсах 2030, млн | B13: =Рынок!G43 -> 724.10112
A15: Площадки: онлайн-продажи (выбранный сценарий)
A16: Площадка | B16: 2025 | C16: 2030 | D16: Рост, раз | E16: Доля рынка 2030
A17: =Площадки!A5 -> Kaspi Магазин | B17: =Площадки!B5 -> 2469.5633 | C17: =Площадки!G5 -> 4550.0102 | D17: =IF(B17=0,0,C17/B17) -> 1.8424352 | E17: =IF($B$7=0,0,C17/$B$7) -> 0.40991083
A18: =Площадки!A6 -> Wildberries | B18: =Площадки!B6 -> 313.78655 | C18: =Площадки!G6 -> 848.07347 | D18: =IF(B18=0,0,C18/B18) -> 2.7027082 | E18: =IF($B$7=0,0,C18/$B$7) -> 0.076403015
A19: =Площадки!A7 -> Ozon | B19: =Площадки!B7 -> 101.84895 | C19: =Площадки!G7 -> 310.81833 | D19: =IF(B19=0,0,C19/B19) -> 3.0517578 | E19: =IF($B$7=0,0,C19/$B$7) -> 0.028001651
A20: =Площадки!A8 -> Halyk Market | B20: =Площадки!B8 -> 123.5955 | C20: =Площадки!G8 -> 217.8175 | D20: =IF(B20=0,0,C20/B20) -> 1.7623417 | E20: =IF($B$7=0,0,C20/$B$7) -> 0.019623198
A23: Сравнение сценариев: рынок всего
A24: Сценарий | B24: 2025 | C24: 2026 | D24: 2027 | E24: 2028 | F24: 2029 | G24: 2030
A25: Пессимистичный | B25: =Рынок!B9 -> 4920 | C25: =Рынок!C9 -> 5389.368 | D25: =Рынок!D9 -> 5903.8622 | E25: =Рынок!E9 -> 6467.8505 | F25: =Рынок!F9 -> 7086.1257 | G25: =Рынок!G9 -> 7763.9477
A26: Базовый | B26: =Рынок!B19 -> 4920 | C26: =Рынок!C19 -> 5770.9046 | D26: =Рынок!D19 -> 6779.3688 | E26: =Рынок!E19 -> 7976.8519 | F26: =Рынок!F19 -> 9401.5632 | G26: =Рынок!G19 -> 11100
A27: Оптимистичный | B27: =Рынок!B29 -> 4920 | C27: =Рынок!C29 -> 5918.76 | D27: =Рынок!D29 -> 7128.9816 | E27: =Рынок!E29 -> 8597.5996 | F27: =Рынок!F29 -> 10382.481 | G27: =Рынок!G29 -> 12555.089

Sheet Допущения
A1: Допущения модели рынка e-commerce Казахстана (млрд ₸, если не указано иное)
A3: Выбранный сценарий (выберите из списка) | C3: Базовый
A4: Номер сценария (служебная ячейка) | C4: =MATCH(C3,$C$20:$E$20,0) -> 2
A6: База 2025 года
A7: Рынок e-commerce 2025, всего (внутренний + трансграничный) | C7: 4920
A8: Доля внутреннего сегмента в 2025 | C8: 0.77
A9: Внутренний рынок 2025 по БНС | C9: 3768.8
A10: Доля e-commerce в рознице 2025 (БНС) | C10: 0.143
A11: Розничная торговля 2025 | C11: =C9/C10 -> 26355.245
A12: Номинальный рост розницы в год | C12: 0.09
A13: Продажи через маркетплейсы 2025 (БНС) | C13: 3237.5
A14: Доля маркетплейсов во внутреннем рынке 2025 | C14: =C13/C9 -> 0.85902675
A15: Средний курс ₸/$ 2025 | C15: 521.5
A16: Заказы на маркетплейсах 2025, млн | C16: 291
A18: Калибровка базового сценария по прогнозу Mastercard | G18: Рынок 2030 по Mastercard | H18: 11100
G19: Доля трансграничного сегмента 2030 | H19: 0.32
A20: Параметр | C20: Пессимистичный | D20: Базовый | E20: Оптимистичный | F20: Выбранный
A21: Рост внутреннего сегмента в год | C21: 0.1 | D21: =((H18*(1-H19))/(C7*C8))^(1/5)-1 -> 0.14782377 | E21: 0.18 | F21: =INDEX(C21:E21,$C$4) -> 0.14782377
A22: Рост трансграничного сегмента в год | C22: 0.08 | D22: =((H18*H19)/(C7*(1-C8)))^(1/5)-1 -> 0.25705999 | E22: 0.28 | F22: =INDEX(C22:E22,$C$4) -> 0.25705999
A23: Рост числа заказов в год | C23: 0.12 | D23: 0.2 | E23: 0.25 | F23: =INDEX(C23:E23,$C$4) -> 0.2
A26: Площадки: онлайн-выручка 2025 (Forbes Kazakhstan 2026) и рост по сценариям
A27: Площадка | B27: Выручка 2025, $ млн | C27: Рост в год: Пессимистичный | D27: Рост в год: Базовый | E27: Рост в год: Оптимистичный | F27: Рост в год: выбранный
A28: Kaspi Магазин | B28: 4735.5 | C28: 0.09 | D28: 0.13 | E28: 0.17 | F28: =INDEX(C28:E28,$C$4) -> 0.13
A29: Wildberries | B29: 601.7 | C29: 0.12 | D29: 0.22 | E29: 0.3 | F29: =INDEX(C29:E29,$C$4) -> 0.22
A30: Ozon | B30: 195.3 | C30: 0.12 | D30: 0.25 | E30: 0.35 | F30: =INDEX(C30:E30,$C$4) -> 0.25
A31: Halyk Market | B31: 237 | C31: 0.06 | D31: 0.12 | E31: 0.18 | F31: =INDEX(C31:E31,$C$4) -> 0.12
A34: Чувствительность: доля покупок в рассрочку/кредит (для листа «Финансирование»)
A35: Доля финансируемых покупок, вариант 1 | C35: 0.2
A36: Доля финансируемых покупок, вариант 2 | C36: 0.3
A37: Доля финансируемых покупок, вариант 3 | C37: 0.4
A40: Легенда
A41: Синий текст | C41: вводные данные (можно менять)
A42: Чёрный текст | C42: формулы (не трогать)
A43: Зелёный текст | C43: ссылки на другие листы
A44: Жёлтая заливка | C44: ключевые допущения и выбор сценария
A46: Примечания к ячейкам (комментарии) содержат источник каждой цифры.

Sheet Рынок
A1: Сценарии рынка e-commerce Казахстана, млрд ₸
A3: Показатель | B3: 2025 | C3: 2026 | D3: 2027 | E3: 2028 | F3: 2029 | G3: 2030
A4: Лет от базы (служебная строка) | B4: 0 | C4: 1 | D4: 2 | E4: 3 | F4: 4 | G4: 5
A6: Сценарий: Пессимистичный
A7: Внутренний сегмент | B7: =Допущения!$C$7*Допущения!$C$8*(1+Допущения!$C$21)^B$4 -> 3788.4 | C7: =Допущения!$C$7*Допущения!$C$8*(1+Допущения!$C$21)^C$4 -> 4167.24 | D7: =Допущения!$C$7*Допущения!$C$8*(1+Допущения!$C$21)^D$4 -> 4583.964 | E7: =Допущения!$C$7*Допущения!$C$8*(1+Допущения!$C$21)^E$4 -> 5042.3604 | F7: =Допущения!$C$7*Допущения!$C$8*(1+Допущения!$C$21)^F$4 -> 5546.5964 | G7: =Допущения!$C$7*Допущения!$C$8*(1+Допущения!$C$21)^G$4 -> 6101.2561
A8: Трансграничный сегмент | B8: =Допущения!$C$7*(1-Допущения!$C$8)*(1+Допущения!$C$22)^B$4 -> 1131.6 | C8: =Допущения!$C$7*(1-Допущения!$C$8)*(1+Допущения!$C$22)^C$4 -> 1222.128 | D8: =Допущения!$C$7*(1-Допущения!$C$8)*(1+Допущения!$C$22)^D$4 -> 1319.8982 | E8: =Допущения!$C$7*(1-Допущения!$C$8)*(1+Допущения!$C$22)^E$4 -> 1425.4901 | F8: =Допущения!$C$7*(1-Допущения!$C$8)*(1+Допущения!$C$22)^F$4 -> 1539.5293 | G8: =Допущения!$C$7*(1-Допущения!$C$8)*(1+Допущения!$C$22)^G$4 -> 1662.6917
A9: Рынок всего | B9: =B7+B8 -> 4920 | C9: =C7+C8 -> 5389.368 | D9: =D7+D8 -> 5903.8622 | E9: =E7+E8 -> 6467.8505 | F9: =F7+F8 -> 7086.1257 | G9: =G7+G8 -> 7763.9477
A10: Доля трансграничного | B10: =IF(B9=0,0,B8/B9) -> 0.23 | C10: =IF(C9=0,0,C8/C9) -> 0.22676648 | D10: =IF(D9=0,0,D8/D9) -> 0.22356522 | E10: =IF(E9=0,0,E8/E9) -> 0.22039627 | F10: =IF(F9=0,0,F8/F9) -> 0.21725967 | G10: =IF(G9=0,0,G8/G9) -> 0.21415544
A11: Розничная торговля | B11: =Допущения!$C$11*(1+Допущения!$C$12)^B$4 -> 26355.245 | C11: =Допущения!$C$11*(1+Допущения!$C$12)^C$4 -> 28727.217 | D11: =Допущения!$C$11*(1+Допущения!$C$12)^D$4 -> 31312.666 | E11: =Допущения!$C$11*(1+Допущения!$C$12)^E$4 -> 34130.806 | F11: =Допущения!$C$11*(1+Допущения!$C$12)^F$4 -> 37202.579 | G11: =Допущения!$C$11*(1+Допущения!$C$12)^G$4 -> 40550.811
A12: Доля внутреннего e-com в рознице | B12: =IF(B11=0,0,B7/B11) -> 0.14374368 | C12: =IF(C11=0,0,C7/C11) -> 0.14506243 | D12: =IF(D11=0,0,D7/D11) -> 0.14639328 | E12: =IF(E11=0,0,E7/E11) -> 0.14773634 | F12: =IF(F11=0,0,F7/F11) -> 0.14909172 | G12: =IF(G11=0,0,G7/G11) -> 0.15045953
A13: Заказы на маркетплейсах, млн | B13: =Допущения!$C$16*(1+Допущения!$C$23)^B$4 -> 291 | C13: =Допущения!$C$16*(1+Допущения!$C$23)^C$4 -> 325.92 | D13: =Допущения!$C$16*(1+Допущения!$C$23)^D$4 -> 365.0304 | E13: =Допущения!$C$16*(1+Допущения!$C$23)^E$4 -> 408.83405 | F13: =Допущения!$C$16*(1+Допущения!$C$23)^F$4 -> 457.89413 | G13: =Допущения!$C$16*(1+Допущения!$C$23)^G$4 -> 512.84143
A14: Рост рынка в год 2025–2030 (CAGR) | B14: =(G9/B9)^(1/5)-1 -> 0.095528046
A16: Сценарий: Базовый
A17: Внутренний сегмент | B17: =Допущения!$C$7*Допущения!$C$8*(1+Допущения!$D$21)^B$4 -> 3788.4 | C17: =Допущения!$C$7*Допущения!$C$8*(1+Допущения!$D$21)^C$4 -> 4348.4156 | D17: =Допущения!$C$7*Допущения!$C$8*(1+Допущения!$D$21)^D$4 -> 4991.2147 | E17: =Допущения!$C$7*Допущения!$C$8*(1+Допущения!$D$21)^E$4 -> 5729.0349 | F17: =Допущения!$C$7*Допущения!$C$8*(1+Допущения!$D$21)^F$4 -> 6575.9224 | G17: =Допущения!$C$7*Допущения!$C$8*(1+Допущения!$D$21)^G$4 -> 7548
A18: Трансграничный сегмент | B18: =Допущения!$C$7*(1-Допущения!$C$8)*(1+Допущения!$D$22)^B$4 -> 1131.6 | C18: =Допущения!$C$7*(1-Допущения!$C$8)*(1+Допущения!$D$22)^C$4 -> 1422.4891 | D18: =Допущения!$C$7*(1-Допущения!$C$8)*(1+Допущения!$D$22)^D$4 -> 1788.1541 | E18: =Допущения!$C$7*(1-Допущения!$C$8)*(1+Допущения!$D$22)^E$4 -> 2247.817 | F18: =Допущения!$C$7*(1-Допущения!$C$8)*(1+Допущения!$D$22)^F$4 -> 2825.6408 | G18: =Допущения!$C$7*(1-Допущения!$C$8)*(1+Допущения!$D$22)^G$4 -> 3552
A19: Рынок всего | B19: =B17+B18 -> 4920 | C19: =C17+C18 -> 5770.9046 | D19: =D17+D18 -> 6779.3688 | E19: =E17+E18 -> 7976.8519 | F19: =F17+F18 -> 9401.5632 | G19: =G17+G18 -> 11100
A20: Доля трансграничного | B20: =IF(B19=0,0,B18/B19) -> 0.23 | C20: =IF(C19=0,0,C18/C19) -> 0.24649326 | D20: =IF(D19=0,0,D18/D19) -> 0.2637641 | E20: =IF(E19=0,0,E18/E19) -> 0.2817925 | F20: =IF(F19=0,0,F18/F19) -> 0.3005501 | G20: =IF(G19=0,0,G18/G19) -> 0.32
A21: Розничная торговля | B21: =Допущения!$C$11*(1+Допущения!$C$12)^B$4 -> 26355.245 | C21: =Допущения!$C$11*(1+Допущения!$C$12)^C$4 -> 28727.217 | D21: =Допущения!$C$11*(1+Допущения!$C$12)^D$4 -> 31312.666 | E21: =Допущения!$C$11*(1+Допущения!$C$12)^E$4 -> 34130.806 | F21: =Допущения!$C$11*(1+Допущения!$C$12)^F$4 -> 37202.579 | G21: =Допущения!$C$11*(1+Допущения!$C$12)^G$4 -> 40550.811
A22: Доля внутреннего e-com в рознице | B22: =IF(B21=0,0,B17/B21) -> 0.14374368 | C22: =IF(C21=0,0,C17/C21) -> 0.15136919 | D22: =IF(D21=0,0,D17/D21) -> 0.15939922 | E22: =IF(E21=0,0,E17/E21) -> 0.16785525 | F22: =IF(F21=0,0,F17/F21) -> 0.17675985 | G22: =IF(G21=0,0,G17/G21) -> 0.18613684
A23: Заказы на маркетплейсах, млн | B23: =Допущения!$C$16*(1+Допущения!$D$23)^B$4 -> 291 | C23: =Допущения!$C$16*(1+Допущения!$D$23)^C$4 -> 349.2 | D23: =Допущения!$C$16*(1+Допущения!$D$23)^D$4 -> 419.04 | E23: =Допущения!$C$16*(1+Допущения!$D$23)^E$4 -> 502.848 | F23: =Допущения!$C$16*(1+Допущения!$D$23)^F$4 -> 603.4176 | G23: =Допущения!$C$16*(1+Допущения!$D$23)^G$4 -> 724.10112
A24: Рост рынка в год 2025–2030 (CAGR) | B24: =(G19/B19)^(1/5)-1 -> 0.17671577
A26: Сценарий: Оптимистичный
A27: Внутренний сегмент | B27: =Допущения!$C$7*Допущения!$C$8*(1+Допущения!$E$21)^B$4 -> 3788.4 | C27: =Допущения!$C$7*Допущения!$C$8*(1+Допущения!$E$21)^C$4 -> 4470.312 | D27: =Допущения!$C$7*Допущения!$C$8*(1+Допущения!$E$21)^D$4 -> 5274.9682 | E27: =Допущения!$C$7*Допущения!$C$8*(1+Допущения!$E$21)^E$4 -> 6224.4624 | F27: =Допущения!$C$7*Допущения!$C$8*(1+Допущения!$E$21)^F$4 -> 7344.8657 | G27: =Допущения!$C$7*Допущения!$C$8*(1+Допущения!$E$21)^G$4 -> 8666.9415
A28: Трансграничный сегмент | B28: =Допущения!$C$7*(1-Допущения!$C$8)*(1+Допущения!$E$22)^B$4 -> 1131.6 | C28: =Допущения!$C$7*(1-Допущения!$C$8)*(1+Допущения!$E$22)^C$4 -> 1448.448 | D28: =Допущения!$C$7*(1-Допущения!$C$8)*(1+Допущения!$E$22)^D$4 -> 1854.0134 | E28: =Допущения!$C$7*(1-Допущения!$C$8)*(1+Допущения!$E$22)^E$4 -> 2373.1372 | F28: =Допущения!$C$7*(1-Допущения!$C$8)*(1+Допущения!$E$22)^F$4 -> 3037.6156 | G28: =Допущения!$C$7*(1-Допущения!$C$8)*(1+Допущения!$E$22)^G$4 -> 3888.148
A29: Рынок всего | B29: =B27+B28 -> 4920 | C29: =C27+C28 -> 5918.76 | D29: =D27+D28 -> 7128.9816 | E29: =E27+E28 -> 8597.5996 | F29: =F27+F28 -> 10382.481 | G29: =G27+G28 -> 12555.089
A30: Доля трансграничного | B30: =IF(B29=0,0,B28/B29) -> 0.23 | C30: =IF(C29=0,0,C28/C29) -> 0.24472153 | D30: =IF(D29=0,0,D28/D29) -> 0.26006708 | E30: =IF(E29=0,0,E28/E29) -> 0.27602323 | F30: =IF(F29=0,0,F28/F29) -> 0.29257126 | G30: =IF(G29=0,0,G28/G29) -> 0.309687
A31: Розничная торговля | B31: =Допущения!$C$11*(1+Допущения!$C$12)^B$4 -> 26355.245 | C31: =Допущения!$C$11*(1+Допущения!$C$12)^C$4 -> 28727.217 | D31: =Допущения!$C$11*(1+Допущения!$C$12)^D$4 -> 31312.666 | E31: =Допущения!$C$11*(1+Допущения!$C$12)^E$4 -> 34130.806 | F31: =Допущения!$C$11*(1+Допущения!$C$12)^F$4 -> 37202.579 | G31: =Допущения!$C$11*(1+Допущения!$C$12)^G$4 -> 40550.811
A32: Доля внутреннего e-com в рознице | B32: =IF(B31=0,0,B27/B31) -> 0.14374368 | C32: =IF(C31=0,0,C27/C31) -> 0.15561243 | D32: =IF(D31=0,0,D27/D31) -> 0.16846116 | E32: =IF(E31=0,0,E27/E31) -> 0.1823708 | F32: =IF(F31=0,0,F27/F31) -> 0.19742894 | G32: =IF(G31=0,0,G27/G31) -> 0.21373041
A33: Заказы на маркетплейсах, млн | B33: =Допущения!$C$16*(1+Допущения!$E$23)^B$4 -> 291 | C33: =Допущения!$C$16*(1+Допущения!$E$23)^C$4 -> 363.75 | D33: =Допущения!$C$16*(1+Допущения!$E$23)^D$4 -> 454.6875 | E33: =Допущения!$C$16*(1+Допущения!$E$23)^E$4 -> 568.35938 | F33: =Допущения!$C$16*(1+Допущения!$E$23)^F$4 -> 710.44922 | G33: =Допущения!$C$16*(1+Допущения!$E$23)^G$4 -> 888.06152
A34: Рост рынка в год 2025–2030 (CAGR) | B34: =(G29/B29)^(1/5)-1 -> 0.20606563
A36: ВЫБРАННЫЙ СЦЕНАРИЙ (см. «Допущения»!C3)
A37: Внутренний сегмент | B37: =CHOOSE(Допущения!$C$4,B7,B17,B27) -> 3788.4 | C37: =CHOOSE(Допущения!$C$4,C7,C17,C27) -> 4348.4156 | D37: =CHOOSE(Допущения!$C$4,D7,D17,D27) -> 4991.2147 | E37: =CHOOSE(Допущения!$C$4,E7,E17,E27) -> 5729.0349 | F37: =CHOOSE(Допущения!$C$4,F7,F17,F27) -> 6575.9224 | G37: =CHOOSE(Допущения!$C$4,G7,G17,G27) -> 7548
A38: Трансграничный сегмент | B38: =CHOOSE(Допущения!$C$4,B8,B18,B28) -> 1131.6 | C38: =CHOOSE(Допущения!$C$4,C8,C18,C28) -> 1422.4891 | D38: =CHOOSE(Допущения!$C$4,D8,D18,D28) -> 1788.1541 | E38: =CHOOSE(Допущения!$C$4,E8,E18,E28) -> 2247.817 | F38: =CHOOSE(Допущения!$C$4,F8,F18,F28) -> 2825.6408 | G38: =CHOOSE(Допущения!$C$4,G8,G18,G28) -> 3552
A39: Рынок всего | B39: =CHOOSE(Допущения!$C$4,B9,B19,B29) -> 4920 | C39: =CHOOSE(Допущения!$C$4,C9,C19,C29) -> 5770.9046 | D39: =CHOOSE(Допущения!$C$4,D9,D19,D29) -> 6779.3688 | E39: =CHOOSE(Допущения!$C$4,E9,E19,E29) -> 7976.8519 | F39: =CHOOSE(Допущения!$C$4,F9,F19,F29) -> 9401.5632 | G39: =CHOOSE(Допущения!$C$4,G9,G19,G29) -> 11100
A40: Доля трансграничного | B40: =CHOOSE(Допущения!$C$4,B10,B20,B30) -> 0.23 | C40: =CHOOSE(Допущения!$C$4,C10,C20,C30) -> 0.24649326 | D40: =CHOOSE(Допущения!$C$4,D10,D20,D30) -> 0.2637641 | E40: =CHOOSE(Допущения!$C$4,E10,E20,E30) -> 0.2817925 | F40: =CHOOSE(Допущения!$C$4,F10,F20,F30) -> 0.3005501 | G40: =CHOOSE(Допущения!$C$4,G10,G20,G30) -> 0.32
A41: Розничная торговля | B41: =CHOOSE(Допущения!$C$4,B11,B21,B31) -> 26355.245 | C41: =CHOOSE(Допущения!$C$4,C11,C21,C31) -> 28727.217 | D41: =CHOOSE(Допущения!$C$4,D11,D21,D31) -> 31312.666 | E41: =CHOOSE(Допущения!$C$4,E11,E21,E31) -> 34130.806 | F41: =CHOOSE(Допущения!$C$4,F11,F21,F31) -> 37202.579 | G41: =CHOOSE(Допущения!$C$4,G11,G21,G31) -> 40550.811
A42: Доля внутреннего e-com в рознице | B42: =CHOOSE(Допущения!$C$4,B12,B22,B32) -> 0.14374368 | C42: =CHOOSE(Допущения!$C$4,C12,C22,C32) -> 0.15136919 | D42: =CHOOSE(Допущения!$C$4,D12,D22,D32) -> 0.15939922 | E42: =CHOOSE(Допущения!$C$4,E12,E22,E32) -> 0.16785525 | F42: =CHOOSE(Допущения!$C$4,F12,F22,F32) -> 0.17675985 | G42: =CHOOSE(Допущения!$C$4,G12,G22,G32) -> 0.18613684
A43: Заказы на маркетплейсах, млн | B43: =CHOOSE(Допущения!$C$4,B13,B23,B33) -> 291 | C43: =CHOOSE(Допущения!$C$4,C13,C23,C33) -> 349.2 | D43: =CHOOSE(Допущения!$C$4,D13,D23,D33) -> 419.04 | E43: =CHOOSE(Допущения!$C$4,E13,E23,E33) -> 502.848 | F43: =CHOOSE(Допущения!$C$4,F13,F23,F33) -> 603.4176 | G43: =CHOOSE(Допущения!$C$4,G13,G23,G33) -> 724.10112
A44: Рост рынка в год 2025–2030 (CAGR) | B44: =(G39/B39)^(1/5)-1 -> 0.17671577

Sheet Площадки
A1: Потенциал онлайн-продаж крупнейших площадок, млрд ₸
A2: Выбранный сценарий: | B2: =Допущения!C3 -> Базовый
A4: Площадка | B4: 2025 | C4: 2026 | D4: 2027 | E4: 2028 | F4: 2029 | G4: 2030 | H4: Рост в год (выбр.) | I4: 2030: Пессимистичный | J4: 2030: Базовый | K4: 2030: Оптимистичный
A5: Kaspi Магазин | B5: =Допущения!$B$28*Допущения!$C$15/1000 -> 2469.5633 | C5: =$B5*(1+Допущения!$F$28)^Рынок!C$4 -> 2790.6065 | D5: =$B5*(1+Допущения!$F$28)^Рынок!D$4 -> 3153.3853 | E5: =$B5*(1+Допущения!$F$28)^Рынок!E$4 -> 3563.3254 | F5: =$B5*(1+Допущения!$F$28)^Рынок!F$4 -> 4026.5577 | G5: =$B5*(1+Допущения!$F$28)^Рынок!G$4 -> 4550.0102 | H5: =Допущения!F28 -> 0.13 | I5: =$B5*(1+Допущения!C28)^5 -> 3799.7292 | J5: =$B5*(1+Допущения!D28)^5 -> 4550.0102 | K5: =$B5*(1+Допущения!E28)^5 -> 5414.3891
A6: Wildberries | B6: =Допущения!$B$29*Допущения!$C$15/1000 -> 313.78655 | C6: =$B6*(1+Допущения!$F$29)^Рынок!C$4 -> 382.81959 | D6: =$B6*(1+Допущения!$F$29)^Рынок!D$4 -> 467.0399 | E6: =$B6*(1+Допущения!$F$29)^Рынок!E$4 -> 569.78868 | F6: =$B6*(1+Допущения!$F$29)^Рынок!F$4 -> 695.14219 | G6: =$B6*(1+Допущения!$F$29)^Рынок!G$4 -> 848.07347 | H6: =Допущения!F29 -> 0.22 | I6: =$B6*(1+Допущения!C29)^5 -> 552.99912 | J6: =$B6*(1+Допущения!D29)^5 -> 848.07347 | K6: =$B6*(1+Допущения!E29)^5 -> 1165.0675
A7: Ozon | B7: =Допущения!$B$30*Допущения!$C$15/1000 -> 101.84895 | C7: =$B7*(1+Допущения!$F$30)^Рынок!C$4 -> 127.31119 | D7: =$B7*(1+Допущения!$F$30)^Рынок!D$4 -> 159.13898 | E7: =$B7*(1+Допущения!$F$30)^Рынок!E$4 -> 198.92373 | F7: =$B7*(1+Допущения!$F$30)^Рынок!F$4 -> 248.65466 | G7: =$B7*(1+Допущения!$F$30)^Рынок!G$4 -> 310.81833 | H7: =Допущения!F30 -> 0.25 | I7: =$B7*(1+Допущения!C30)^5 -> 179.49265 | J7: =$B7*(1+Допущения!D30)^5 -> 310.81833 | K7: =$B7*(1+Допущения!E30)^5 -> 456.6941
A8: Halyk Market | B8: =Допущения!$B$31*Допущения!$C$15/1000 -> 123.5955 | C8: =$B8*(1+Допущения!$F$31)^Рынок!C$4 -> 138.42696 | D8: =$B8*(1+Допущения!$F$31)^Рынок!D$4 -> 155.0382 | E8: =$B8*(1+Допущения!$F$31)^Рынок!E$4 -> 173.64278 | F8: =$B8*(1+Допущения!$F$31)^Рынок!F$4 -> 194.47991 | G8: =$B8*(1+Допущения!$F$31)^Рынок!G$4 -> 217.8175 | H8: =Допущения!F31 -> 0.12 | I8: =$B8*(1+Допущения!C31)^5 -> 165.39866 | J8: =$B8*(1+Допущения!D31)^5 -> 217.8175 | K8: =$B8*(1+Допущения!E31)^5 -> 282.75656
A9: Итого 4 площадки | B9: =SUM(B5:B8) -> 3008.7942 | C9: =SUM(C5:C8) -> 3439.1642 | D9: =SUM(D5:D8) -> 3934.6024 | E9: =SUM(E5:E8) -> 4505.6806 | F9: =SUM(F5:F8) -> 5164.8345 | G9: =SUM(G5:G8) -> 5926.7195 | I9: =SUM(I5:I8) -> 4697.6196 | J9: =SUM(J5:J8) -> 5926.7195 | K9: =SUM(K5:K8) -> 7318.9073
A10: Рынок всего (выбранный сценарий) | B10: =Рынок!B39 -> 4920 | C10: =Рынок!C39 -> 5770.9046 | D10: =Рынок!D39 -> 6779.3688 | E10: =Рынок!E39 -> 7976.8519 | F10: =Рынок!F39 -> 9401.5632 | G10: =Рынок!G39 -> 11100
A11: Остальной рынок (прочие площадки, сайты, трансграничные) | B11: =B10-B9 -> 1911.2058 | C11: =C10-C9 -> 2331.7404 | D11: =D10-D9 -> 2844.7664 | E11: =E10-E9 -> 3471.1713 | F11: =F10-F9 -> 4236.7287 | G11: =G10-G9 -> 5173.2805
A12: Доля 4 площадок в рынке | B12: =IF(B10=0,0,B9/B10) -> 0.61154355 | C12: =IF(C10=0,0,C9/C10) -> 0.59594889 | D12: =IF(D10=0,0,D9/D10) -> 0.58037887 | E12: =IF(E10=0,0,E9/E10) -> 0.56484446 | F12: =IF(F10=0,0,F9/F10) -> 0.54935912 | G12: =IF(G10=0,0,G9/G10) -> 0.53393869
A13: Доля Kaspi Магазин в рынке | B13: =IF(B10=0,0,B5/B10) -> 0.50194375 | C13: =IF(C10=0,0,C5/C10) -> 0.48356482 | D13: =IF(D10=0,0,D5/D10) -> 0.46514438 | E13: =IF(E10=0,0,E5/E10) -> 0.44670823 | F13: =IF(F10=0,0,F5/F10) -> 0.42828598 | G13: =IF(G10=0,0,G5/G10) -> 0.40991083
A15: Примечание: 2025 — онлайн-выручка по Forbes Kazakhstan 2026 (только продажи на собственной площадке, не GMV), пересчитанная в ₸ по курсу из «Допущения»!C15. Темпы роста — допущения модели.

Sheet Категории
A1: Категории: продажи через маркетплейсы, млрд ₸
A3: Категория | B3: Доля 2025 (БНС) | C3: Объём 2025 | D3: Доля 2030 (допущение) | E3: Объём 2030 (выбр. сценарий) | F3: Рост, раз
A4: Доля маркетплейсов во внутреннем рынке 2030 (допущение) | D4: =Допущения!C14 -> 0.85902675
A6: Телефоны и гаджеты | B6: 0.171 | C6: =Допущения!$C$13*B6 -> 553.6125 | D6: =B6 -> 0.171 | E6: =Рынок!$G$37*$D$4*D6 -> 1108.7527 | F6: =IF(C6=0,0,E6/C6) -> 2.0027595
A7: Одежда, обувь и спорттовары | B7: 0.124 | C7: =Допущения!$C$13*B7 -> 401.45 | D7: =B7 -> 0.124 | E7: =Рынок!$G$37*$D$4*D7 -> 804.0078 | F7: =IF(C7=0,0,E7/C7) -> 2.0027595
A8: Товары для дома и дачи | B8: 0.121 | C8: =Допущения!$C$13*B8 -> 391.7375 | D8: =B8 -> 0.121 | E8: =Рынок!$G$37*$D$4*D8 -> 784.556 | F8: =IF(C8=0,0,E8/C8) -> 2.0027595
A9: Бытовая техника | B9: 0.103 | C9: =Допущения!$C$13*B9 -> 333.4625 | D9: =B9 -> 0.103 | E9: =Рынок!$G$37*$D$4*D9 -> 667.84519 | F9: =IF(C9=0,0,E9/C9) -> 2.0027595
A10: Продукты питания | B10: 0.074 | C10: =Допущения!$C$13*B10 -> 239.575 | D10: =B10 -> 0.074 | E10: =Рынок!$G$37*$D$4*D10 -> 479.81111 | F10: =IF(C10=0,0,E10/C10) -> 2.0027595
A11: Прочие категории | B11: =1-SUM(B6:B10) -> 0.407 | C11: =Допущения!$C$13*B11 -> 1317.6625 | D11: =1-SUM(D6:D10) -> 0.407 | E11: =Рынок!$G$37*$D$4*D11 -> 2638.9611 | F11: =IF(C11=0,0,E11/C11) -> 2.0027595
A12: Итого маркетплейсы | B12: =SUM(B6:B11) -> 1 | C12: =SUM(C6:C11) -> 3237.5 | D12: =SUM(D6:D11) -> 1 | E12: =SUM(E6:E11) -> 6483.9339 | F12: =IF(C12=0,0,E12/C12) -> 2.0027595
A14: Тренды: электроника теряет долю (рассрочка ограничена), продукты онлайн растут быстрее всех (Kaspi e-Grocery +53% в 2025), одежда и дом растут за счёт WB, Ozon и трансграничной торговли.

Sheet Финансирование
A1: Потенциал для банков: объём покупок в рассрочку/кредит в 2030 году, млрд ₸
A2: Сопоставление, а не прогноз: фактическая доля рассрочки в e-commerce не публикуется.
A4: Доля финансируемых покупок | B4: Внутренний рынок 2030: Пессимистичный | C4: Базовый | D4: Оптимистичный
A5: =Допущения!C35 -> 0.2 | B5: =$A5*Рынок!$G$7 -> 1220.2512 | C5: =$A5*Рынок!$G$17 -> 1509.6 | D5: =$A5*Рынок!$G$27 -> 1733.3883
A6: =Допущения!C36 -> 0.3 | B6: =$A6*Рынок!$G$7 -> 1830.3768 | C6: =$A6*Рынок!$G$17 -> 2264.4 | D6: =$A6*Рынок!$G$27 -> 2600.0824
A7: =Допущения!C37 -> 0.4 | B7: =$A7*Рынок!$G$7 -> 2440.5024 | C7: =$A7*Рынок!$G$17 -> 3019.2 | D7: =$A7*Рынок!$G$27 -> 3466.7766
A9: Справочно, 2025: внутренний рынок × те же доли
A10: =Допущения!C35 -> 0.2 | B10: =$A10*Рынок!$B$37 -> 757.68
A11: =Допущения!C36 -> 0.3 | B11: =$A11*Рынок!$B$37 -> 1136.52
A12: =Допущения!C37 -> 0.4 | B12: =$A12*Рынок!$B$37 -> 1515.36
A14: Контекст: у Kaspi BNPL — 41% объёма финтех-платформы (FY2025). Ограничения АРРФР: КДН 50%, ГЭСВ ≤ 46%, срок беззалоговых ≤ 5 лет, с 2027 г. планируется коэффициент долга к доходу.

Sheet История
A1: Розничная электронная коммерция РК, БНС (внутренний рынок)
A3: Год | B3: Объём, млрд ₸ | C3: Рост к прошлому году | D3: Доля в рознице
A4: 2021 | B4: 482 | C4: — | D4: 0.036
A5: 2022* | B5: 1963.5 | C5: н/с | D5: 0.125
A6: 2023* | B6: 2439.8 | C6: =B6/B5-1 -> 0.24257703 | D6: 0.127
A7: 2024* | B7: 3156.4 | C7: =B7/B6-1 -> 0.2937126 | D7: 0.141
A8: 2025* | B8: 3768.8 | C8: =B8/B7-1 -> 0.1940185 | D8: 0.143
A10: * С 2022 года — с учётом маркетплейсов; рост 2022 к 2021 несопоставим (смена методики).
A12: Альтернативные оценки 2025 года
A13: Источник | B13: Объём 2025, млрд ₸ | C13: Рост | D13: Комментарий
A14: БНС | B14: 3768.8 | C14: 0.19 | D14: Внутренний рынок; маркетплейсы 86%
A15: Mastercard (авг. 2026) | B15: 4920 | C15: 0.25 | D15: Включая трансграничную торговлю (23%); доля в рознице 18%
A16: Baker Tilly (сент. 2026) | B16: 4313 | C16: 0.127 | D16: Маркетплейсы 93%; прогноз 2026: 4 437 млрд ₸ (+2,9%)

Sheet Партнёры
A1: Партнёры маркетплейсов
A3: Площадка | B3: Банки и финансы | C3: Платежи | D3: Логистика | E3: Собственники и стратегические партнёры
A4: Kaspi | B4: Kaspi Bank: BNPL (41% объёма финтеха), Kaspi Red, кредиты продавцам (18%) | C4: Kaspi Pay, Kaspi QR, Kaspi Gold | D4: 10 000+ Kaspi Postomat, Kaspi Доставка; пилот с Казпочтой (Hepsiburada → Казахстан) | E4: Доля в Magnum E-com; контроль Kolesa Group (50,76% голосов); Hepsiburada (Турция)
A5: Wildberries | B5: Казахстанские банки-партнёры (кредит с окт. 2025, рассрочка с фев. 2026), Home Credit Bank (карта Ozen); Вайлдберриз Банк (РФ); МФО Solva — переговоры не подтверждены | C5: Карты банков РК | D5: Склады Астана + Алматы 260 тыс. м² (1 кв. 2027), аренда ~46 тыс. м², логоцентр на западе, ПВЗ | E5: Группа RWB (Wildberries + Russ)
A6: Ozon | B6: Рассрочка: Halyk Bank, Home Credit Bank, Евразийский банк, МФО «Фридом Финанс Кредит» (на запуск, 2023); Ozon Банк (РФ) | C6: Карты банков РК | D6: ПВЗ | E6: Ozon (РФ)
A7: Halyk Market | B7: Halyk Bank (владелец), рассрочка и кредит Halyk | C7: Homebank, карты банков РК | D7: — | E7: Экосистема Halyk (Halyk Travel и др.)
A8: Freedom (Arbuz, Ticketon, Freedom Travel) | B8: Freedom Bank | C8: Freedom Pay, Freedom SuperApp (2,59 млн MAU) | D8: Собственная доставка Arbuz | E8: Freedom Holding
A9: Teez | B9: Покупатель — крупный финтех (не раскрыт) | C9: — | D9: — | E9: Сделка на этапе due diligence
A10: Ритейлеры (Sulpak, Technodom, Alser, Evrika, Mechta) | B10: Halyk (отдельные продукты рассрочки), ForteBank (Sulpak, Technodom), Kaspi (Sulpak) | C10: Карты, Kaspi QR | D10: Собственные магазины + Kaspi | E10: —

Sheet Источники
A1: Источники
A3: Источник | B3: Ссылка
A4: БНС: Об электронной коммерции в РК (2025) | B4: https://stat.gov.kz/ru/industries/economy/local-market/publications/346330/
A5: Mastercard: Исследование рынка розничного e-commerce в Казахстане (авг. 2026) | B5: https://www.mastercard.com/content/dam/mccom/eeu/kazakhstan/documents/20260909_KZ_eCom_CAFS_Short.pdf
A6: Kapital.kz: К 2030 году объём e-commerce может достичь 11 трлн тенге | B6: https://kapital.kz/economic/152916/k-2030-godu-obuem-e-commerce-v-kazahstane-mozhet-dostich-11-trln-tenge.html
A7: Baker Tilly: Market Overview of E-Commerce in Kazakhstan 2026 | B7: https://bakertilly-ca.com/wp-content/uploads/2026/09/e-commerce-market-review-of-kazakhstan-2026-presentation..pdf
A8: Forbes.kz: 50 крупнейших торговых интернет-площадок — 2026 | B8: https://forbes.kz/articles/50-krupneyshih-torgovyh-internet-ploshadok-kazahstana-2026
A9: Kaspi.kz 4Q & FY 2025 Results | B9: https://ir.kaspi.kz/media/4Q__FY_2025_Financial_Results_.pdf
A10: Kaspi.kz 2Q & 1H 2026 Results | B10: https://ir.kaspi.kz/media/2Q_2026_Results.pdf
A11: Inbusiness.kz: почти 300 млн заказов на маркетплейсах в 2025 | B11: https://inbusiness.kz/ru/last/pochti-300-mln-zakazov-sdelali-kazahstancy-na-marketplejsah-v-2025-godu
A12: Repost: склады WB 260 тыс. м² за $100 млн | B12: https://repost.news/news/134770-wildberriec_postroit_v_kazakhstane_sklady_na_260_tysjach_kvadratnyh_metrov_za_100_millionov
A13: LSM.kz: ограничения АРРФР для заёмщиков и банков | B13: https://lsm.kz/zakreditovannost-mery-arrfr
A14: Kursiv: новые правила для покупок на AliExpress, Temu, iHerb | B14: https://kz.kursiv.media/2026-06-06/svvo-chto-izmenitsya-dlya-pokupatelei-aliexpress-temu-i-iherb-v-kazahstane/
A15: Полный текстовый отчёт: docs/kz-ecommerce-market-potential.md (в репозитории)
